pyfys/__init__.py
pyfys/constants.py
pyfys/main.py
pyfys/masses.py
pyfys/test.py
pyfys-0.2.15.dist-info/LICENCE
pyfys-0.2.15.dist-info/METADATA
pyfys-0.2.15.dist-info/WHEEL
pyfys-0.2.15.dist-info/top_level.txt
pyfys-0.2.15.dist-info/RECORD
