Metadata-Version: 2.1
Name: pyfys
Version: 0.2.15
Summary: A library to speed up physics work
Home-page: https://github.com/nikolaiborbe
Author: Nikolai G. Borbe
Author-email: nikolaiborbe@gmail.com
Keywords: python,physics,graphing,constants
Classifier: Development Status :: 1 - Planning
Classifier: Intended Audience :: Developers
Classifier: Programming Language :: Python :: 3
Classifier: Operating System :: Unix
Classifier: Operating System :: MacOS :: MacOS X
Classifier: Operating System :: Microsoft :: Windows
License-File: LICENCE
Requires-Dist: matplotlib
Requires-Dist: numpy
